README.rst
csample.py
setup.py
csample.egg-info/PKG-INFO
csample.egg-info/SOURCES.txt
csample.egg-info/dependency_links.txt
csample.egg-info/entry_points.txt
csample.egg-info/requires.txt
csample.egg-info/top_level.txt